pystr/__init__.py
pystr/pystr.py
pystr-1.2.dist-info/METADATA
pystr-1.2.dist-info/WHEEL
pystr-1.2.dist-info/top_level.txt
pystr-1.2.dist-info/RECORD
