Metadata-Version: 2.1
Name: pystr
Version: 1.2
Summary: 可以自动输入字符（包括汉字）
Home-page: UNKNOWN
License: 许可证
Keywords: 输入,汉字
Platform: any
Requires-Dist: PyAutoGUI
Requires-Dist: pyperclip
